sigmate/__init__.py
sigmate/cli/__init__.py
sigmate/cli/clean.py
sigmate/cli/configure.py
sigmate/cli/sign.py
sigmate/cli/trust.py
sigmate/cli/verify.py
sigmate/config.py
sigmate/managers/config.py
sigmate/sbom/__init__.py
sigmate/sbom/generate.py
sigmate/secops/__init__.py
sigmate/secops/keys.py
sigmate/secops/signing.py
sigmate/secops/trust.py
sigmate/services/__init__.py
sigmate/services/signer.py
sigmate/services/verifier.py
sigmate/utils/__init__.py
sigmate/utils/checksum_parser.py
sigmate/utils/files.py
sigmate/utils/git.py
sigmate/utils/hashing.py
sigmate/utils/ignore.py
sigmate/utils/logger.py
sigmate/utils/print.py
sigmate-1.0.0.dist-info/METADATA
sigmate-1.0.0.dist-info/WHEEL
sigmate-1.0.0.dist-info/entry_points.txt
sigmate-1.0.0.dist-info/RECORD
