Metadata-Version: 2.3
Name: sigmate
Version: 1.0.0
Summary: A secure file signing and verification CLI with metadata
License: MIT
Keywords: signing,verification,cli,sbom,cryptography,trust
Author: Lucian BLETAN
Author-email: neuraluc@gmail.com
Requires-Python: >=3.10,<4.0
Classifier: Development Status :: 4 - Beta
Classifier: Environment :: Console
Classifier: Intended Audience :: Developers
Classifier: License :: OSI Approved :: MIT License
Classifier: Operating System :: MacOS
Classifier: Operating System :: POSIX
Classifier: Operating System :: Unix
Classifier: Programming Language :: Python
Classifier: Programming Language :: Python :: 3
Classifier: Programming Language :: Python :: 3.10
Classifier: Programming Language :: Python :: 3.11
Classifier: Programming Language :: Python :: 3.12
Classifier: Programming Language :: Python :: 3.13
Classifier: Topic :: Software Development :: Libraries :: Python Modules
Requires-Dist: click (>=8.1,<9.0)
Requires-Dist: cryptography (>=42.0,<43.0)
Project-URL: Homepage, https://github.com/opensecurity/sigmate-py
Project-URL: Repository, https://github.com/opensecurity/sigmate-py
